02_adder/full_adder_gate.v
`timescale 1ps/1ps

module half_adder (
    input A,
    input B,
    output Sum,
    output Carry
);

assign Sum = A ^ B;
assign Carry = A & B;

endmodule

module full_adder (
    input A,
    input B,
    input C,
    output Sum,
    output Cout
);

wire w1;
wire w2;
wire w3;

assign w1 = A ^ B;
assign w2 = A & B;
assign Sum = w1 ^ C;
assign w3 = w1 & C;
assign Cout = w2 | w3;

endmodule

02_adder/full_adder_gate_tb.v
`timescale 1ps/1ps

module full_adder_tb;
    // inputs
    reg A;
    reg B;
    reg C;

    // outputs
    wire Sum;
    wire Cout;

    wire [2:0] ABC;
    assign ABC = {A, B, C};

    // Instantiate the full adder
    full_adder uut (
        .A(A),
        .B(B),
        .C(C),
        .Sum(Sum),
        .Cout(Cout)
    );

    initial begin
        $dumpfile("full_adder_gate.vcd");
        $dumpvars(0, full_adder_tb);

        $display("A B C | Sum Cout");
        $display("--------------");
        $monitor("%b %b %b |  %b   %b", A, B, C, Sum, Cout);

        A = 0; B = 0; C = 0; #10;
        A = 0; B = 0; C = 1; #10;
        A = 0; B = 1; C = 0; #10;
        A = 0; B = 1; C = 1; #10;
        A = 1; B = 0; C = 0; #10;
        A = 1; B = 0; C = 1; #10;
        A = 1; B = 1; C = 0; #10;
        A = 1; B = 1; C = 1; #10;

        $finish;
    end
endmodule

02_adder/full_adder_gate.vcd
$date
	Sat Aug 08 16:26:43 2026
$end
$version
	Icarus Verilog
$end
$timescale
	1ps
$end
$scope module full_adder_tb $end
$var wire 1 ! Sum $end
$var wire 1 " Cout $end
$var wire 3 # ABC [2:0] $end
$var reg 1 $ A $end
$var reg 1 % B $end
$var reg 1 & C $end
$scope module uut $end
$var wire 1 $ A $end
$var wire 1 % B $end
$var wire 1 & C $end
$var wire 1 " Cout $end
$var wire 1 ! Sum $end
$var wire 1 ' w1 $end
$var wire 1 ( w2 $end
$var wire 1 ) w3 $end
$upscope $end
$upscope $end
$enddefinitions $end
#0
$dumpvars
0)
0(
0'
0&
0%
0$
b0 #
0"
0!
$end
#10
1!
b1 #
1&
#20
1'
0&
b10 #
1%
#30
1"
0!
1)
b11 #
1&
#40
0"
1!
0)
0&
0%
b100 #
1$
#50
1"
0!
1)
b101 #
1&
#60
0)
0'
1(
0&
b110 #
1%
#70
1!
b111 #
1&
