02_adder/full_sub_gate.v


module full_sub(
    input  wire A,
    input  wire B,
    input  wire C,
    output wire Diff,
    output wire Bout
);

wire w1;
wire w2;
wire w3;
wire w4;

assign w1 = A ^ B;
assign w2 = ~w1 & C;
assign w3 = ~A & B;
assign w4 = w2 | w3;
assign Diff = w1 ^ C;
assign Bout = w4;

endmodule

02_adder/full_sub_gate_tb.v
`timescale 1ps/1ps

module full_sub_gate_tb;
    // inputs
    reg A;
    reg B;
    reg C;

    // outputs
    wire Diff;
    wire Bout;

    // Instantiate full subtractor
    full_sub uut (
        .A(A),
        .B(B),
        .C(C),
        .Diff(Diff),
        .Bout(Bout)
    );

    initial begin
        $dumpfile("full_sub_gate.vcd");
        $dumpvars(0, full_sub_gate_tb);

        $display("A B C | Diff Bout");
        $display("--------------");
        $monitor("%b %b %b |  %b    %b", A, B, C, Diff, Bout);

        A = 0; B = 0; C = 0; #10;
        A = 0; B = 0; C = 1; #10;
        A = 0; B = 1; C = 0; #10;
        A = 0; B = 1; C = 1; #10;
        A = 1; B = 0; C = 0; #10;
        A = 1; B = 0; C = 1; #10;
        A = 1; B = 1; C = 0; #10;
        A = 1; B = 1; C = 1; #10;

        $finish;
    end
endmodule

02_adder/full_sub_gate.vcd
$date
	Sat Aug 08 16:48:12 2026
$end
$version
	Icarus Verilog
$end
$timescale
	1ps
$end
$scope module full_sub_gate_tb $end
$var wire 1 ! Diff $end
$var wire 1 " Bout $end
$var reg 1 # A $end
$var reg 1 $ B $end
$var reg 1 % C $end
$scope module uut $end
$var wire 1 # A $end
$var wire 1 $ B $end
$var wire 1 " Bout $end
$var wire 1 % C $end
$var wire 1 ! Diff $end
$var wire 1 & w1 $end
$var wire 1 ' w2 $end
$var wire 1 ( w3 $end
$var wire 1 ) w4 $end
$upscope $end
$upscope $end
$enddefinitions $end
#0
$dumpvars
0)
0(
0'
0&
0%
0$
0#
0"
0!
$end
#10
1"
1)
1'
1!
1%
#20
0'
1&
1(
0%
1$
#30
0!
1%
#40
0"
0)
1!
0(
0%
0$
1#
#50
0!
1%
#60
0&
0%
1$
#70
1"
1)
1'
1!
1%
